oog/__init__.py
oog/environment.py
oog/shapes.py
oog/sprite.py
oog/action_spaces/__init__.py
oog/action_spaces/abstract_action_space.py
oog/action_spaces/composite.py
oog/action_spaces/grid.py
oog/action_spaces/joystick.py
oog/action_spaces/set_position.py
oog/env_wrappers/__init__.py
oog/env_wrappers/abstract_wrapper.py
oog/env_wrappers/gym_wrapper.py
oog/env_wrappers/logger.py
oog/env_wrappers/multi_agent.py
oog/env_wrappers/simulation.py
oog/game_rules/__init__.py
oog/game_rules/abstract_rule.py
oog/game_rules/change_layer.py
oog/game_rules/conditional.py
oog/game_rules/contact_rules.py
oog/game_rules/create_sprites.py
oog/game_rules/fixation.py
oog/game_rules/modify_meta_state.py
oog/game_rules/modify_sprites.py
oog/game_rules/portal.py
oog/game_rules/re_center.py
oog/game_rules/task_phases.py
oog/game_rules/timing.py
oog/game_rules/vanish.py
oog/maze_lib/__init__.py
oog/maze_lib/maze.py
oog/maze_lib/maze_generators.py
oog/observers/__init__.py
oog/observers/abstract_observer.py
oog/observers/color_maps.py
oog/observers/pil_renderer.py
oog/observers/polygon_modifiers.py
oog/observers/raw_state.py
oog/physics/__init__.py
oog/physics/abstract_force.py
oog/physics/abstract_physics.py
oog/physics/collisions.py
oog/physics/constant_speed.py
oog/physics/distance_fn_force.py
oog/physics/friction.py
oog/physics/gravity.py
oog/physics/maze_physics.py
oog/physics/maze_walk.py
oog/physics/physics.py
oog/physics/random_force.py
oog/physics/tether_physics.py
oog/state_initialization/__init__.py
oog/state_initialization/distributions.py
oog/state_initialization/sprite_generators.py
oog/tasks/__init__.py
oog/tasks/abstract_task.py
oog/tasks/composite_task.py
oog/tasks/contact_reward.py
oog/tasks/reset.py
oog/tasks/stay_alive.py
oog_demos/__init__.py
oog_demos/gif_writer.py
oog_demos/gui_frames.py
oog_demos/human_agent.py
oog_demos/restore_logged_data.py
oog_demos/run_demo.py
oog_demos/example_configs/__init__.py
oog_demos/example_configs/bounce_box_contact_prediction.py
oog-1.1.dist-info/LICENSE
oog-1.1.dist-info/LICENSE-spriteworld
oog-1.1.dist-info/METADATA
oog-1.1.dist-info/WHEEL
oog-1.1.dist-info/top_level.txt
oog-1.1.dist-info/RECORD
