Metadata-Version: 2.1
Name: oog
Version: 1.1
Summary: Object-Oriented Games is a python-based game engine.
Home-page: https://github.com/jazlab/oog.github.io
Author: Nicholas Watters
License: MIT license
Keywords: ai,reinforcement-learning,python,machine learning,objects,psychology,neurophysiology,psychophysics,physics,environment
Platform: UNKNOWN
Classifier: Development Status :: 3 - Alpha
Classifier: Environment :: Console
Classifier: Intended Audience :: Science/Research
Classifier: License :: OSI Approved :: MIT License
Classifier: Operating System :: POSIX :: Linux
Classifier: Operating System :: Microsoft :: Windows
Classifier: Operating System :: MacOS :: MacOS X
Classifier: Programming Language :: Python :: 3.7
Classifier: Programming Language :: Python :: 3.8
Classifier: Topic :: Scientific/Engineering
Requires-Dist: spriteworld
Requires-Dist: imageio
Requires-Dist: mss
